{"stats":{"minecraft:dropped":{"item_sorter:sorter":1,"minecraft:hopper":1,"minecraft:grass_block":3,"minecraft:chest":1},"minecraft:used":{"item_sorter:sorter":85,"minecraft:debug_stick":9,"minecraft:dirt":2,"minecraft:hopper":64,"minecraft:crafting_table":1,"minecraft:grass_block":44,"minecraft:chest":63,"item_sorter:improved_sorter":2},"minecraft:custom":{"minecraft:time_since_rest":92497,"minecraft:open_chest":174,"minecraft:crouch_one_cm":2319,"minecraft:play_time":92497,"minecraft:sprint_one_cm":3068,"minecraft:walk_one_cm":91620,"minecraft:sneak_time":2155,"minecraft:drop":6,"minecraft:jump":73,"minecraft:inspect_hopper":142,"minecraft:leave_game":41,"minecraft:time_since_death":92497,"minecraft:total_world_time":145153,"minecraft:interact_with_crafting_table":1,"minecraft:fly_one_cm":30464},"minecraft:crafted":{"item_sorter:filter":1},"minecraft:picked_up":{"minecraft:stone":1,"minecraft:deepslate":64,"item_sorter:sorter":1,"minecraft:redstone_ore":64,"minecraft:oak_log":64,"minecraft:grass_block":536,"item_sorter:filter":2,"minecraft:chest":2,"minecraft:hopper":1507}},"DataVersion":3465}